__init__.py
wiretap_sqlserver/__init__.py
wiretap_sqlserver/sqlserverhandler.py
wiretap_sqlserver-5.0.0.dist-info/METADATA
wiretap_sqlserver-5.0.0.dist-info/WHEEL
wiretap_sqlserver-5.0.0.dist-info/top_level.txt
wiretap_sqlserver-5.0.0.dist-info/RECORD
