Metadata-Version: 2.1
Name: wiretap-sqlserver
Version: 5.0.0
Author: he-dev
Project-URL: GitHub, https://github.com/he-dev/wiretap-py
Requires-Python: >=3.10
Requires-Dist: pyodbc
